setup.py
distributions_elham/Binomialdistribution.py
distributions_elham/Gaussiandistribution.py
distributions_elham/Generaldistribution.py
distributions_elham/__init__.py
distributions_elham.egg-info/PKG-INFO
distributions_elham.egg-info/SOURCES.txt
distributions_elham.egg-info/dependency_links.txt
distributions_elham.egg-info/not-zip-safe
distributions_elham.egg-info/top_level.txt